LICENSE
MANIFEST.in
README.md
setup.py
pewn/__init__.py
pewn/classes.py
pewn/http.py
pewn/meta.py
pewn/utils.py
pewn.egg-info/PKG-INFO
pewn.egg-info/SOURCES.txt
pewn.egg-info/dependency_links.txt
pewn.egg-info/requires.txt
pewn.egg-info/top_level.txt