Metadata-Version: 2.1
Name: pewn
Version: 0.1.1
Summary: 📦 Another Python library for downloading files from URL.
Home-page: https://github.com/5elenay/pewn/
Author: 5elenay
Author-email: 
License: MIT
Project-URL: Bug Tracker, https://github.com/5elenay/pewn/issues
Keywords: python,download,pewn,async,download-file
Platform: UNKNOWN
Classifier: Development Status :: 5 - Production/Stable
Classifier: Intended Audience :: Developers
Classifier: Operating System :: OS Independent
Classifier: License :: OSI Approved :: MIT License
Classifier: Programming Language :: Python :: 3
Requires-Python: >=3.6.0
